scrollbound/__init__.py
scrollbound/game.py
scrollbound/data/__init__.py
scrollbound/data/cards.json
scrollbound/data/enemies.json
scrollbound/data/scrolls.json
scrollbound-1.0.1.dist-info/licenses/LICENSE
scrollbound-1.0.1.dist-info/METADATA
scrollbound-1.0.1.dist-info/WHEEL
scrollbound-1.0.1.dist-info/entry_points.txt
scrollbound-1.0.1.dist-info/top_level.txt
scrollbound-1.0.1.dist-info/RECORD
