Metadata-Version: 2.4
Name: scrollbound
Version: 1.0.1
Summary: mini-roguelite game about descending a dungeon while fighting monsters with spell and scroll cards
Author-email: Ruby <ruby@enhancedrock.tech>
License:                     GNU GENERAL PUBLIC LICENSE
Requires-Python: >=3.10
License-File: LICENSE
Requires-Dist: rich>=13.9.4
Requires-Dist: rich-menu>=0.3.0
Requires-Dist: importlib-resources>=1.3.0; python_version < "3.9"
Dynamic: license-file
